opfunu/__init__.py
opfunu/benchmark.py
opfunu/cec_based/__init__.py
opfunu/cec_based/cec.py
opfunu/cec_based/cec2005.py
opfunu/cec_based/cec2008.py
opfunu/cec_based/cec2010.py
opfunu/cec_based/cec2013.py
opfunu/cec_based/cec2014.py
opfunu/cec_based/cec2015.py
opfunu/cec_based/cec2017.py
opfunu/cec_based/cec2019.py
opfunu/cec_based/cec2020.py
opfunu/cec_based/cec2021.py
opfunu/cec_based/cec2022.py
opfunu/cec_based/data_2005/E_ScafferF6_M_D10.txt
opfunu/cec_based/data_2005/E_ScafferF6_M_D30.txt
opfunu/cec_based/data_2005/E_ScafferF6_M_D50.txt
opfunu/cec_based/data_2005/Files List and some explaination.txt
opfunu/cec_based/data_2005/ackley_M_D10.txt
opfunu/cec_based/data_2005/ackley_M_D30.txt
opfunu/cec_based/data_2005/ackley_M_D50.txt
opfunu/cec_based/data_2005/data_EF8F2.txt
opfunu/cec_based/data_2005/data_E_ScafferF6.txt
opfunu/cec_based/data_2005/data_ackley.txt
opfunu/cec_based/data_2005/data_griewank.txt
opfunu/cec_based/data_2005/data_high_cond_elliptic_rot.txt
opfunu/cec_based/data_2005/data_hybrid_func1.txt
opfunu/cec_based/data_2005/data_hybrid_func2.txt
opfunu/cec_based/data_2005/data_hybrid_func3.txt
opfunu/cec_based/data_2005/data_hybrid_func4.txt
opfunu/cec_based/data_2005/data_rastrigin.txt
opfunu/cec_based/data_2005/data_rosenbrock.txt
opfunu/cec_based/data_2005/data_schwefel_102.txt
opfunu/cec_based/data_2005/data_schwefel_206.txt
opfunu/cec_based/data_2005/data_schwefel_213.txt
opfunu/cec_based/data_2005/data_sphere.txt
opfunu/cec_based/data_2005/data_weierstrass.txt
opfunu/cec_based/data_2005/elliptic_M_D10.txt
opfunu/cec_based/data_2005/elliptic_M_D30.txt
opfunu/cec_based/data_2005/elliptic_M_D50.txt
opfunu/cec_based/data_2005/global_optima.txt
opfunu/cec_based/data_2005/griewank_M_D10.txt
opfunu/cec_based/data_2005/griewank_M_D30.txt
opfunu/cec_based/data_2005/griewank_M_D50.txt
opfunu/cec_based/data_2005/hybrid_func1_M_D10.txt
opfunu/cec_based/data_2005/hybrid_func1_M_D30.txt
opfunu/cec_based/data_2005/hybrid_func1_M_D50.txt
opfunu-1.0.4.dist-info/LICENSE
opfunu-1.0.4.dist-info/METADATA
opfunu-1.0.4.dist-info/WHEEL
opfunu-1.0.4.dist-info/top_level.txt
opfunu-1.0.4.dist-info/RECORD
