Metadata-Version: 2.1
Name: opfunu
Version: 1.0.4
Summary: Opfunu: An Open-source Python Library for Optimization Benchmark Functions
Home-page: https://github.com/thieu1995/opfunu
Author: Thieu
Author-email: nguyenthieu2102@gmail.com
License: GPLv3
Project-URL: Documentation, https://opfunu.readthedocs.io/
Project-URL: Source Code, https://github.com/thieu1995/opfunu
Project-URL: Bug Tracker, https://github.com/thieu1995/opfunu/issues
Project-URL: Change Log, https://github.com/thieu1995/opfunu/blob/master/ChangeLog.md
Project-URL: Forum, https://t.me/+fRVCJGuGJg1mNDg1
Keywords: optimization functions,test functions,benchmark functions,mathematical functions,CEC competitions,CEC-2008,CEC-2009,CEC-2010,CEC-2011,CEC-2012,CEC-2013,CEC-2014,CEC-2015,CEC-2017,CEC-2019,CEC-2020,CEC-2021,CEC-2022,soft computing,Stochastic optimization,Global optimization,Convergence analysis,Search space exploration,Local search,Computational intelligence,Performance analysis,Exploration versus exploitation,Constrained optimization,Simulations
Classifier: Development Status :: 5 - Production/Stable
Classifier: Intended Audience :: Developers
Classifier: Intended Audience :: Education
Classifier: Intended Audience :: Information Technology
Classifier: Intended Audience :: Science/Research
Classifier: License :: OSI Approved :: GNU General Public License v3 (GPLv3)
Classifier: Natural Language :: English
Classifier: Programming Language :: Python :: 3
Classifier: Programming Language :: Python :: 3.7
Classifier: Programming Language :: Python :: 3.8
Classifier: Programming Language :: Python :: 3.9
Classifier: Programming Language :: Python :: 3.10
Classifier: Programming Language :: Python :: 3.11
Classifier: Topic :: System :: Benchmark
Classifier: Topic :: Scientific/Engineering
Classifier: Topic :: Scientific/Engineering :: Mathematics
Classifier: Topic :: Scientific/Engineering :: Artificial Intelligence
Classifier: Topic :: Scientific/Engineering :: Information Analysis
Classifier: Topic :: Scientific/Engineering :: Visualization
Classifier: Topic :: Scientific/Engineering :: Bio-Informatics
Classifier: Topic :: Software Development :: Build Tools
Classifier: Topic :: Software Development :: Libraries
Classifier: Topic :: Software Development :: Libraries :: Python Modules
Classifier: Topic :: Utilities
Requires-Python: >=3.7, <3.12
License-File: LICENSE
Requires-Dist: numpy>=1.16.5
Requires-Dist: matplotlib>=3.3.0
Requires-Dist: Pillow>=9.1.0
Requires-Dist: requests>=2.27.0
Provides-Extra: dev
Requires-Dist: pytest>=7.0; extra == "dev"
Requires-Dist: twine>=4.0.1; extra == "dev"
